pstruc/__init__.py
pstruc/_directory_structure.py
pstruc/_file_structure.py
pstruc/_pretty_structure.py
pstruc/file_tools.py
pstruc/pstruc.py
pstruc/version.py
pstruc-1.0.1.dist-info/LICENSE
pstruc-1.0.1.dist-info/METADATA
pstruc-1.0.1.dist-info/WHEEL
pstruc-1.0.1.dist-info/entry_points.txt
pstruc-1.0.1.dist-info/top_level.txt
pstruc-1.0.1.dist-info/RECORD
