Metadata-Version: 2.1
Name: pstruc
Version: 1.0.1
Summary: Get a project file structure to analyze it
Home-page: https://github.com/nachokhan/pstruc
Author: Ignacio Rigoni
Classifier: Programming Language :: Python :: 3
Classifier: License :: OSI Approved :: MIT License
Classifier: Operating System :: OS Independent
Requires-Python: >=3.11.0
License-File: LICENSE
Requires-Dist: colorama ==0.4.6
Requires-Dist: iniconfig ==2.0.0
Requires-Dist: packaging ==23.2
Requires-Dist: pluggy ==1.3.0
Requires-Dist: pytest ==7.4.3
Requires-Dist: PyYAML ==6.0.1
Requires-Dist: setuptools >=40.8.0
Provides-Extra: dev
Requires-Dist: pytest ; extra == 'dev'
